imsearch/__init__.py
imsearch/config.py
imsearch/exception.py
imsearch/extractor.py
imsearch/index.py
imsearch/nmslib.py
imsearch/backend/__init__.py
imsearch/backend/extractor.py
imsearch/backend/feature_extractor.py
imsearch/backend/object_detector/__init__.py
imsearch/backend/object_detector/yolo/__init__.py
imsearch/backend/object_detector/yolo/detector.py
imsearch/backend/object_detector/yolo/models.py
imsearch/backend/object_detector/yolo/utils.py
imsearch/repository/__init__.py
imsearch/repository/mongo.py
imsearch/utils/__init__.py
imsearch/utils/image.py
imsearch-0.1.1.dist-info/LICENSE
imsearch-0.1.1.dist-info/METADATA
imsearch-0.1.1.dist-info/WHEEL
imsearch-0.1.1.dist-info/top_level.txt
imsearch-0.1.1.dist-info/RECORD
