Metadata-Version: 2.1
Name: imsearch
Version: 0.1.1
Summary: A generic framework to build your own reverse image search engine
Home-page: https://github.com/rikenmehta03/imsearch
Author: Riken Mehta
Author-email: riken.mehta03@gmail.com
License: UNKNOWN
Platform: UNKNOWN
Classifier: Programming Language :: Python :: 3
Classifier: License :: OSI Approved :: Apache Software License
Classifier: Operating System :: POSIX :: Linux
Requires-Dist: torch
Requires-Dist: torchvision
Requires-Dist: pandas
Requires-Dist: tables
Requires-Dist: redis
Requires-Dist: pymongo
Requires-Dist: nmslib
Requires-Dist: wget
Requires-Dist: opencv-python
Requires-Dist: requests
